rocmtop/__init__.py
rocmtop/cli.py
rocmtop-0.1.0.dist-info/licenses/LICENSE
rocmtop-0.1.0.dist-info/METADATA
rocmtop-0.1.0.dist-info/WHEEL
rocmtop-0.1.0.dist-info/entry_points.txt
rocmtop-0.1.0.dist-info/top_level.txt
rocmtop-0.1.0.dist-info/RECORD
