Metadata-Version: 2.4
Name: rocmtop
Version: 0.1.0
Summary: A lightweight ROCm GPU monitoring tool (like nvidia-smi top)
License: MIT
Requires-Python: >=3.8
License-File: LICENSE
Requires-Dist: rich
Requires-Dist: readchar
Dynamic: license-file
